dinoscan/__init__.py
dinoscan/__main__.py
dinoscan/analyzers.py
dinoscan/cli.py
dinoscan/core.py
dinoscan-2.0.4.dist-info/METADATA
dinoscan-2.0.4.dist-info/WHEEL
dinoscan-2.0.4.dist-info/entry_points.txt
dinoscan-2.0.4.dist-info/top_level.txt
dinoscan-2.0.4.dist-info/RECORD
