Metadata-Version: 2.4
Name: dinoscan
Version: 2.0.4
Summary: DinoScan - Comprehensive AST-based Python code analysis with real-time diagnostics, security scanning, and intelligent caching
Author-email: DinoScan Team <contact@dinopitstudios.com>
Maintainer-email: DinoScan Team <contact@dinopitstudios.com>
License: MIT
Project-URL: Homepage, https://github.com/DinoPitStudiosllc/DinoScan-VSCode-Extension
Project-URL: Repository, https://github.com/DinoPitStudiosllc/DinoScan-VSCode-Extension
Project-URL: Issues, https://github.com/DinoPitStudiosllc/DinoScan-VSCode-Extension/issues
Project-URL: Documentation, https://github.com/DinoPitStudiosllc/DinoScan-VSCode-Extension#readme
Project-URL: Changelog, https://github.com/DinoPitStudiosllc/DinoScan-VSCode-Extension/releases
Keywords: code-analysis,static-analysis,security,python,linting,ast,dead-code,circular-imports,documentation,duplicates,diagnostics,code-quality,python-analyzer
Classifier: Development Status :: 4 - Beta
Classifier: Intended Audience :: Developers
Classifier: Operating System :: OS Independent
Classifier: Programming Language :: Python :: 3
Classifier: Programming Language :: Python :: 3.9
Classifier: Programming Language :: Python :: 3.10
Classifier: Programming Language :: Python :: 3.11
Classifier: Programming Language :: Python :: 3.12
Classifier: Topic :: Software Development :: Quality Assurance
Classifier: Topic :: Software Development :: Libraries :: Python Modules
Classifier: Topic :: Software Development :: Testing
Classifier: Environment :: Console
Classifier: Typing :: Typed
Requires-Python: >=3.9
Provides-Extra: dev
Requires-Dist: pytest>=7.0.0; extra == "dev"
Requires-Dist: pytest-cov>=4.0.0; extra == "dev"
Requires-Dist: black>=23.0.0; extra == "dev"
Requires-Dist: isort>=5.0.0; extra == "dev"
Requires-Dist: mypy>=1.0.0; extra == "dev"
Requires-Dist: bandit>=1.7.0; extra == "dev"
Requires-Dist: pip-audit>=2.0.0; extra == "dev"
